grc_macronizer/__init__.py
grc_macronizer/ascii.py
grc_macronizer/barytone.py
grc_macronizer/class_macronizer.py
grc_macronizer/class_text.py
grc_macronizer/format_macrons.py
grc_macronizer/morph_disambiguator.py
grc_macronizer/nominal_forms.py
grc_macronizer/sanity_check.py
grc_macronizer/stop_list.py
grc_macronizer/stop_list_epic.py
grc_macronizer/test_bailly.py
grc_macronizer/verbal_forms.py
grc_macronizer/db/__init__.py
grc_macronizer/db/crawl_lsj.py
grc_macronizer/db/custom.py
grc_macronizer/db/custom_epic.py
grc_macronizer/db/hypotactic.pkl
grc_macronizer/db/hypotactic.py
grc_macronizer/db/ionic.py
grc_macronizer/db/lsj.py
grc_macronizer/db/lsj_keys.pkl
grc_macronizer/db/lsj_keys.py
grc_macronizer/db/proper_names.py
grc_macronizer/db/wiktionary_ambiguous.py
grc_macronizer/db/wiktionary_example.py
grc_macronizer/db/wiktionary_old.py
grc_macronizer/db/wiktionary_singletons.py
grc_macronizer/tests/__init__.py
grc_macronizer/tests/anabasis.py
grc_macronizer/tests/hiketides.py
grc_macronizer-1.3.0.dist-info/licenses/LICENSE
grc_macronizer-1.3.0.dist-info/METADATA
grc_macronizer-1.3.0.dist-info/WHEEL
grc_macronizer-1.3.0.dist-info/top_level.txt
grc_macronizer-1.3.0.dist-info/RECORD
