Metadata-Version: 2.4
Name: grc-macronizer
Version: 1.3.0
Summary: A macronizer for Ancient Greek
Author-email: Albin Ruben Johannes Thörn Cleland <albin.thorn_cleland@klass.lu.se>
License-Expression: MIT
Project-URL: Homepage, https://github.com/Urdatorn/grc_macronizer
Classifier: Programming Language :: Python :: 3
Classifier: Topic :: Text Processing :: Linguistic
Classifier: Intended Audience :: Science/Research
Classifier: Operating System :: OS Independent
Requires-Python: ==3.12.*
License-File: LICENSE
Requires-Dist: grc_utils==0.2.0
Requires-Dist: spacy<3.8.0,>=3.7.4
Requires-Dist: grc_odycy_joint_trf==0.7.0
Requires-Dist: lxml
Requires-Dist: tqdm>=4.65.0
Requires-Dist: xxhash
Provides-Extra: dev
Dynamic: license-file
